sort_lines.py
sort_lines-0.3.0.dist-info/LICENSE
sort_lines-0.3.0.dist-info/METADATA
sort_lines-0.3.0.dist-info/WHEEL
sort_lines-0.3.0.dist-info/entry_points.txt
sort_lines-0.3.0.dist-info/top_level.txt
sort_lines-0.3.0.dist-info/RECORD
