Metadata-Version: 2.1
Name: sort_lines
Version: 0.3.0
Summary: alphabetize lines in files
Author: Samuel Searles-Bryant
Author-email: sam@samueljsb.co.uk
License: MIT
Project-URL: Source, https://github.com/samueljsb/sort-lines
Project-URL: Changelog, https://github.com/samueljsb/sort-lines/blob/main/CHANGELOG.md
Classifier: License :: OSI Approved :: MIT License
Classifier: Programming Language :: Python :: 3
Classifier: Programming Language :: Python :: 3 :: Only
Classifier: Programming Language :: Python :: Implementation :: CPython
Requires-Python: >=3.9
License-File: LICENSE
